{
  "subject": {
    "title": "A Science of Society",
    "subjectCode": "POLS2112",
    "topics": [
      {
        "title": "Social Science and Modernity",
        "slug": "social-science-and-modernity"
      },
      {
        "title": "Definitions",
        "slug": "definitions"
      },
      {
        "title": "Major social spectacles in the Current World",
        "slug": "major-social-spectacles-in-the-current-world"
      },
      {
        "title": "Class",
        "slug": "class"
      },
      {
        "title": "Gender",
        "slug": "gender"
      },
      {
        "title": "Origin",
        "slug": "origin"
      },
      {
        "title": "Caste and Nation",
        "slug": "caste-and-nation"
      },
      {
        "title": "Socialization and Human Behavior State",
        "slug": "socialization-and-human-behavior-state"
      },
      {
        "title": "The Contemporary State and Colonization",
        "slug": "the-contemporary-state-and-colonization"
      },
      {
        "title": "Nations as Created Units",
        "slug": "nations-as-created-units"
      },
      {
        "title": "Considering State in Pakistan  Economy",
        "slug": "considering-state-in-pakistan-economy"
      },
      {
        "title": "Definition",
        "slug": "definition"
      },
      {
        "title": "Modern Economy",
        "slug": "modern-economy"
      },
      {
        "title": "How Economy affects Society?",
        "slug": "how-economy-affects-society"
      },
      {
        "title": "Economic Sociology History and Knowledge",
        "slug": "economic-sociology-history-and-knowledge"
      },
      {
        "title": "Definitions",
        "slug": "definitions"
      },
      {
        "title": "Colonial Histories and their Present",
        "slug": "colonial-histories-and-their-present"
      },
      {
        "title": "Alternative Ways of Knowing",
        "slug": "alternative-ways-of-knowing"
      },
      {
        "title": "Historical Knowledge Social Movements and Social Change",
        "slug": "historical-knowledge-social-movements-and-social-change"
      },
      {
        "title": "Collective Behavior",
        "slug": "collective-behavior"
      },
      {
        "title": "Social Movements",
        "slug": "social-movements"
      },
      {
        "title": "Social Change",
        "slug": "social-change"
      }
    ]
  }
}